pyclipr/__init__.py
pyclipr/module.cpp
pyclipr/version.py
include/pyclipr/CLIPR_Export.h
pyclipr/__init__.pyi
pyclipr/pyclipr.cp313-win_amd64.pyd
pyclipr/pyclipr.pyi
pyclipr-0.1.8.dist-info/METADATA
pyclipr-0.1.8.dist-info/WHEEL
pyclipr-0.1.8.dist-info/licenses/LICENSE
pyclipr-0.1.8.dist-info/RECORD
