Metadata-Version: 2.4
Name: pyclipr
Version: 0.1.8
Summary: Python library for polygon clipping and offsetting based on Clipper2
Project-URL: Homepage, https://github.com/drlukeparry/pyclipr
Project-URL: Documentation, https://github.com/drlukeparry/pyclipr
Project-URL: Repository, https://github.com/drlukeparry/pyclipr.git
Project-URL: Issues, https://github.com/drlukeparry/pyclipr/issues
Project-URL: Changelog, https://github.com/drlukeparry/pyclipr/blob/main/CHANGELOG.md
Author-email: Luke Parry <dev@lukeparry.uk>, Luktug <contact@luktug.co.uk>
License: Boost Software License - Version 1.0 - August 17th, 2003
License-File: LICENSE
Keywords: Clipper2,clipper,libClipper,line clipping,polygon,polygon boolean,polygon clipping,polygon offsetting
Classifier: Programming Language :: Python
Classifier: Programming Language :: Python :: 3.9
Classifier: Programming Language :: Python :: 3.10
Classifier: Programming Language :: Python :: 3.11
Classifier: Programming Language :: Python :: 3.12
Classifier: Programming Language :: Python :: 3.13
Classifier: Programming Language :: Python :: 3.14
Classifier: Topic :: Scientific/Engineering
Requires-Python: >=3.9
Requires-Dist: numpy>=1.21
